months/__init__.py
months/months.py
months-1.0.0.dist-info/DESCRIPTION.rst
months-1.0.0.dist-info/METADATA
months-1.0.0.dist-info/metadata.json
months-1.0.0.dist-info/RECORD
months-1.0.0.dist-info/top_level.txt
months-1.0.0.dist-info/WHEEL
