Metadata-Version: 2.0
Name: months
Version: 1.0.0
Summary: Python library for representing specific months
Home-page: https://github.com/kstark/months
Author: Kyle Stark
Author-email: kstarked@gmail.com
License: MIT
Keywords: months
Platform: UNKNOWN
Classifier: Development Status :: 2 - Pre-Alpha
Classifier: Intended Audience :: Developers
Classifier: License :: OSI Approved :: MIT License
Classifier: Natural Language :: English
Classifier: Programming Language :: Python :: 2
Classifier: Programming Language :: Python :: 2.6
Classifier: Programming Language :: Python :: 2.7
Classifier: Programming Language :: Python :: 3
Classifier: Programming Language :: Python :: 3.3
Classifier: Programming Language :: Python :: 3.4
